{"731906356654637137":{"workminimum":50,"workmaximum":250,"slutminimum":100,"slutmaximum":350,"crimeminimum":200,"crimemaximum":500,"slutrate":50,"crimerate":75,"isenabled9":1,"deleted_count":2,"log_system":15,"isenabled10":1,"edit_system":4,"isenabled4":1,"cc_system":2,"isenabled1":1,"vcc_system":1,"custom.channelid.thank":false},"721720821311209534":{"workminimum":50,"workmaximum":250,"slutminimum":100,"slutmaximum":350,"crimeminimum":200,"crimemaximum":500,"slutrate":50,"crimerate":75,"isenabled7":1,"mj_system":0,"log_system":58,"isenabled9":1,"deleted_count":1,"isenabled6":1,"cu_system":0,"isenabled10":1,"edit_system":4,"isenabled4":1,"cc_system":24,"isenabled1":1,"vcc_system":12},"731232142830338159":{"workminimum":50,"workmaximum":250,"slutminimum":100,"slutmaximum":350,"crimeminimum":200,"crimemaximum":500,"slutrate":50,"crimerate":75,"isenabled1":1,"vcc_system":16,"log_system":37,"isenabled4":1,"cc_system":21},"732902805005926400":{"workminimum":50,"workmaximum":250,"slutminimum":100,"slutmaximum":350,"crimeminimum":200,"crimemaximum":500,"slutrate":50,"crimerate":75,"isenabled4":1,"cc_system":8,"log_system":87,"isenabled1":1,"vcc_system":11,"isenabled3":1,"ru_system":0,"isenabled11":1,"isenabled7":1,"mj_system":0,"rc_system":1,"isenabled6":1,"cu_system":0,"isenabled9":1,"deleted_count":15,"isenabled10":1,"edit_system":3}}